area_calc/__init__.py
area_calc/main.py
joker_area_calc-1.0.1.dist-info/METADATA
joker_area_calc-1.0.1.dist-info/WHEEL
joker_area_calc-1.0.1.dist-info/top_level.txt
joker_area_calc-1.0.1.dist-info/RECORD
