Metadata-Version: 2.4
Name: joker-area-calc
Version: 1.0.1
Summary: Библиотека для вычисления площади геометрических фигур
Author-email: Абубакр Ахмедов <xspace1902@gmail.com>
Requires-Python: >=3.10
